iscdmidc.py
iscdmidc-0.1.4.dist-info/LICENSE
iscdmidc-0.1.4.dist-info/METADATA
iscdmidc-0.1.4.dist-info/WHEEL
iscdmidc-0.1.4.dist-info/top_level.txt
iscdmidc-0.1.4.dist-info/RECORD
